life/__init__.py
life/cli.py
life/config.py
life/display.py
life/lib/__init__.py
life/lib/ansi.py
life/personas/__init__.py
life/personas/base.py
life/personas/kim.py
life/personas/pepper.py
life/personas/roast.py
life/prompts.py
life/repeats.py
life/sqlite.py
life/tasks.py
life/utils.py
life_cli-0.1.0.dist-info/LICENSE
life_cli-0.1.0.dist-info/METADATA
life_cli-0.1.0.dist-info/WHEEL
life_cli-0.1.0.dist-info/entry_points.txt
life_cli-0.1.0.dist-info/RECORD
