Metadata-Version: 2.3
Name: life-cli
Version: 0.1.0
Summary: Life accountability CLI
Author: tyson
Author-email: tyson.chan@proton.me
Requires-Python: >=3.12,<4.0
Classifier: Programming Language :: Python :: 3
Classifier: Programming Language :: Python :: 3.12
Classifier: Programming Language :: Python :: 3.13
Requires-Dist: pyyaml (>=6.0.3,<7.0.0)
Requires-Dist: typer (>=0.17.4,<0.18.0)
